{
  "tokens": [
    {
      "name": "USD Coin",
      "symbol": "USDC",
      "decimals": 6,
      "networks": {
        "84532": "0xaE5554056c25bd179601bF64A296da0A3851a64d"
      }
    },
    {
      "name": "USD Tether",
      "symbol": "USDT",
      "decimals": 6,
      "networks": {
        "84532": "0xB4a65206bFBCA641332d080D1ac6283524A92783"
      }
    },
    {
      "name": "Wrapped Bitcoin",
      "symbol": "WBTC",
      "decimals": 6,
      "networks": {
        "84532": "0xFfeFA49F787e3168Cc1B97BB0261800512633033"
      }
    },
    {
      "name": "Eigenlayer",
      "symbol": "EIGEN",
      "decimals": 6,
      "networks": {
        "84532": "0xad49B39b79721557bc536Ae1069336D5F36f8642"
      }
    }
  ]
}
